[
  {
    "id": 1,
    "name": "RATUL HASSAN",
    "email": "ratul.hassan21@polytech.edu.bd",
    "phone": "+8801710443322",
    "department": "Mechanical",
    "semester": 6,
    "cgpa": 3.42,
    "attendance": 88,
    "image": "https://via.placeholder.com/150",
    "status": "active"
  },
  {
    "id": 2,
    "name": "MD. SAMAUN ISLAM TANVIR",
    "email": "samaun.tanvir@polytech.edu.bd",
    "phone": "+8801821554433",
    "department": "Electrical",
    "semester": 6,
    "cgpa": 3.15,
    "attendance": 76,
    "image": "https://via.placeholder.com/150",
    "status": "active"
  },
  {
    "id": 3,
    "name": "SAYED ISMAM HOSSEN",
    "email": "ismam.hossen@polytech.edu.bd",
    "phone": "+8801912665544",
    "department": "Civil",
    "semester": 6,
    "cgpa": 3.82,
    "attendance": 94,
    "image": "https://via.placeholder.com/150",
    "status": "active"
  },
  {
    "id": 4,
    "name": "MD. AZIM",
    "email": "md.azim@polytech.edu.bd",
    "phone": "+8801513776655",
    "department": "Mechanical",
    "semester": 6,
    "cgpa": 2.95,
    "attendance": 62,
    "image": "https://via.placeholder.com/150",
    "status": "inactive"
  },
  {
    "id": 5,
    "name": "MD. MARUF HASAN",
    "email": "maruf.hasan@polytech.edu.bd",
    "phone": "+8801614887766",
    "department": "Electrical",
    "semester": 6,
    "cgpa": 3.65,
    "attendance": 89,
    "image": "https://via.placeholder.com/150",
    "status": "active"
  },
  {
    "id": 6,
    "name": "RASEL MIA",
    "email": "rasel.mia@polytech.edu.bd",
    "phone": "+8801315998877",
    "department": "Civil",
    "semester": 6,
    "cgpa": 3.1,
    "attendance": 72,
    "image": "https://via.placeholder.com/150",
    "status": "active"
  },
  {
    "id": 7,
    "name": "MAHMUDUR RAHMAN",
    "email": "mahmudur.rahman@polytech.edu.bd",
    "phone": "+8801716009988",
    "department": "Mechanical",
    "semester": 6,
    "cgpa": 3.55,
    "attendance": 85,
    "image": "https://via.placeholder.com/150",
    "status": "active"
  },
  {
    "id": 8,
    "name": "BAPON BARAI",
    "email": "bapon.barai@polytech.edu.bd",
    "phone": "+8801817110099",
    "department": "Electrical",
    "semester": 6,
    "cgpa": 3.9,
    "attendance": 98,
    "image": "https://via.placeholder.com/150",
    "status": "active"
  },
  {
    "id": 9,
    "name": "JOY BHOWMIK",
    "email": "joy.bhowmik@polytech.edu.bd",
    "phone": "+8801918221100",
    "department": "Civil",
    "semester": 6,
    "cgpa": 2.8,
    "attendance": 68,
    "image": "https://via.placeholder.com/150",
    "status": "active"
  },
  {
    "id": 10,
    "name": "FAHIM IMTIYAZ",
    "email": "fahim.imtiyaz@polytech.edu.bd",
    "phone": "+8801519332211",
    "department": "Mechanical",
    "semester": 6,
    "cgpa": 3.3,
    "attendance": 81,
    "image": "https://via.placeholder.com/150",
    "status": "active"
  },
  {
    "id": 11,
    "name": "MD. SUMON HOWLADER",
    "email": "sumon.howlader@polytech.edu.bd",
    "phone": "+8801620443322",
    "department": "Electrical",
    "semester": 6,
    "cgpa": 3.2,
    "attendance": 79,
    "image": "https://via.placeholder.com/150",
    "status": "active"
  },
  {
    "id": 12,
    "name": "HIMEL MAHMUD JITU",
    "email": "himel.jitu@polytech.edu.bd",
    "phone": "+8801721554433",
    "department": "Civil",
    "semester": 6,
    "cgpa": 3.48,
    "attendance": 87,
    "image": "https://via.placeholder.com/150",
    "status": "active"
  },
  {
    "id": 13,
    "name": "M. K. MAHIN KHAN",
    "email": "mahin.khan@polytech.edu.bd",
    "phone": "+8801822665544",
    "department": "Mechanical",
    "semester": 6,
    "cgpa": 3.75,
    "attendance": 92,
    "image": "https://via.placeholder.com/150",
    "status": "active"
  },
  {
    "id": 14,
    "name": "SWARTHO",
    "email": "swartho.poly@polytech.edu.bd",
    "phone": "+8801923776655",
    "department": "Electrical",
    "semester": 6,
    "cgpa": 2.65,
    "attendance": 55,
    "image": "https://via.placeholder.com/150",
    "status": "inactive"
  },
  {
    "id": 15,
    "name": "MD. REDOAN",
    "email": "redoan.md@polytech.edu.bd",
    "phone": "+8801524887766",
    "department": "Civil",
    "semester": 6,
    "cgpa": 3.4,
    "attendance": 84,
    "image": "https://via.placeholder.com/150",
    "status": "active"
  },
  {
    "id": 16,
    "name": "TARIKUL ISLAM RONI",
    "email": "tarikul.roni@polytech.edu.bd",
    "phone": "+8801625998877",
    "department": "Mechanical",
    "semester": 6,
    "cgpa": 3.05,
    "attendance": 73,
    "image": "https://via.placeholder.com/150",
    "status": "active"
  },
  {
    "id": 17,
    "name": "MD. ROFIQUL ISLAM",
    "email": "rofiqul.islam@polytech.edu.bd",
    "phone": "+8801726009988",
    "department": "Electrical",
    "semester": 6,
    "cgpa": 3.28,
    "attendance": 80,
    "image": "https://via.placeholder.com/150",
    "status": "active"
  },
  {
    "id": 18,
    "name": "MD. IMRAN HOWLADER",
    "email": "imran.howlader@polytech.edu.bd",
    "phone": "+8801827110099",
    "department": "Civil",
    "semester": 6,
    "cgpa": 3.5,
    "attendance": 86,
    "image": "https://via.placeholder.com/150",
    "status": "active"
  },
  {
    "id": 19,
    "name": "MD. MOINUL ISLAM ZURAD",
    "email": "moinul.zurad@polytech.edu.bd",
    "phone": "+8801928221100",
    "department": "Mechanical",
    "semester": 6,
    "cgpa": 3.62,
    "attendance": 90,
    "image": "https://via.placeholder.com/150",
    "status": "active"
  },
  {
    "id": 20,
    "name": "MD. SABBIR AHMED",
    "email": "sabbir.ahmed@polytech.edu.bd",
    "phone": "+8801529332211",
    "department": "Electrical",
    "semester": 6,
    "cgpa": 3.18,
    "attendance": 77,
    "image": "https://via.placeholder.com/150",
    "status": "active"
  },
  {
    "id": 21,
    "name": "MD. HASIBUL ISLAM JUHAD",
    "email": "hasibul.juhad@polytech.edu.bd",
    "phone": "+8801630443322",
    "department": "Civil",
    "semester": 6,
    "cgpa": 3.45,
    "attendance": 85,
    "image": "https://via.placeholder.com/150",
    "status": "active"
  },
  {
    "id": 22,
    "name": "MD. ANIK HASAN",
    "email": "anik.hasan@polytech.edu.bd",
    "phone": "+8801731554433",
    "department": "Mechanical",
    "semester": 6,
    "cgpa": 2.9,
    "attendance": 64,
    "image": "https://via.placeholder.com/150",
    "status": "active"
  },
  {
    "id": 23,
    "name": "MD. SABBIR MUNSI",
    "email": "sabbir.munsi@polytech.edu.bd",
    "phone": "+8801832665544",
    "department": "Electrical",
    "semester": 6,
    "cgpa": 3.35,
    "attendance": 82,
    "image": "https://via.placeholder.com/150",
    "status": "active"
  },
  {
    "id": 24,
    "name": "REYAD HASAN RIFAT",
    "email": "reyad.rifat@polytech.edu.bd",
    "phone": "+8801933776655",
    "department": "Civil",
    "semester": 6,
    "cgpa": 3.58,
    "attendance": 88,
    "image": "https://via.placeholder.com/150",
    "status": "active"
  },
  {
    "id": 25,
    "name": "HASAN MORTUJA",
    "email": "hasan.mortuja@polytech.edu.bd",
    "phone": "+8801534887766",
    "department": "Mechanical",
    "semester": 6,
    "cgpa": 3.7,
    "attendance": 93,
    "image": "https://via.placeholder.com/150",
    "status": "active"
  },
  {
    "id": 26,
    "name": "PROSHANTO BAPAREE",
    "email": "proshanto.b@polytech.edu.bd",
    "phone": "+8801635998877",
    "department": "Electrical",
    "semester": 6,
    "cgpa": 3.12,
    "attendance": 75,
    "image": "https://via.placeholder.com/150",
    "status": "active"
  },
  {
    "id": 27,
    "name": "MD. RAKIBUR RAHMAN",
    "email": "rakibur.r@polytech.edu.bd",
    "phone": "+8801736009988",
    "department": "Civil",
    "semester": 6,
    "cgpa": 3.25,
    "attendance": 78,
    "image": "https://via.placeholder.com/150",
    "status": "active"
  },
  {
    "id": 28,
    "name": "NAHID SHARIAR MUNNA",
    "email": "nahid.munna@polytech.edu.bd",
    "phone": "+8801837110099",
    "department": "Mechanical",
    "semester": 6,
    "cgpa": 3.48,
    "attendance": 84,
    "image": "https://via.placeholder.com/150",
    "status": "active"
  },
  {
    "id": 29,
    "name": "DRUBA MITRA",
    "email": "druba.mitra@polytech.edu.bd",
    "phone": "+8801938221100",
    "department": "Electrical",
    "semester": 6,
    "cgpa": 3.52,
    "attendance": 87,
    "image": "https://via.placeholder.com/150",
    "status": "active"
  },
  {
    "id": 30,
    "name": "MD. SHAKIB AL HASAN",
    "email": "shakib.hasan@polytech.edu.bd",
    "phone": "+8801539332211",
    "department": "Civil",
    "semester": 6,
    "cgpa": 3.95,
    "attendance": 99,
    "image": "https://via.placeholder.com/150",
    "status": "active"
  },
  {
    "id": 31,
    "name": "MD. ALOM",
    "email": "md.alom@polytech.edu.bd",
    "phone": "+8801640443322",
    "department": "Mechanical",
    "semester": 6,
    "cgpa": 2.75,
    "attendance": 60,
    "image": "https://via.placeholder.com/150",
    "status": "active"
  },
  {
    "id": 32,
    "name": "MD. REFAT",
    "email": "md.refat@polytech.edu.bd",
    "phone": "+8801741554433",
    "department": "Electrical",
    "semester": 6,
    "cgpa": 3.38,
    "attendance": 83,
    "image": "https://via.placeholder.com/150",
    "status": "active"
  },
  {
    "id": 33,
    "name": "ABU SADAT SAIM",
    "email": "sadat.saim@polytech.edu.bd",
    "phone": "+8801842665544",
    "department": "Civil",
    "semester": 6,
    "cgpa": 3.22,
    "attendance": 78,
    "image": "https://via.placeholder.com/150",
    "status": "active"
  },
  {
    "id": 34,
    "name": "MD. HASNAIN",
    "email": "md.hasnain@polytech.edu.bd",
    "phone": "+8801943776655",
    "department": "Mechanical",
    "semester": 6,
    "cgpa": 3.45,
    "attendance": 85,
    "image": "https://via.placeholder.com/150",
    "status": "active"
  },
  {
    "id": 35,
    "name": "TAHMID RAHMAN",
    "email": "tahmid.rahman@polytech.edu.bd",
    "phone": "+8801544887766",
    "department": "Electrical",
    "semester": 6,
    "cgpa": 3.68,
    "attendance": 91,
    "image": "https://via.placeholder.com/150",
    "status": "active"
  },
  {
    "id": 36,
    "name": "MD. ABU NASER",
    "email": "abu.naser@polytech.edu.bd",
    "phone": "+8801645998877",
    "department": "Civil",
    "semester": 6,
    "cgpa": 2.98,
    "attendance": 66,
    "image": "https://via.placeholder.com/150",
    "status": "active"
  },
  {
    "id": 37,
    "name": "S.M. MOSTAFIZUR RAHMAN",
    "email": "mostafizur.r@polytech.edu.bd",
    "phone": "+8801746009988",
    "department": "Mechanical",
    "semester": 6,
    "cgpa": 3.4,
    "attendance": 84,
    "image": "https://via.placeholder.com/150",
    "status": "active"
  },
  {
    "id": 38,
    "name": "B.M.MAHIDUL ISLAM",
    "email": "mahidul.islam@polytech.edu.bd",
    "phone": "+8801847110099",
    "department": "Electrical",
    "semester": 6,
    "cgpa": 3.55,
    "attendance": 89,
    "image": "https://via.placeholder.com/150",
    "status": "active"
  },
  {
    "id": 39,
    "name": "MD. MAHFUJUR RAHMAN MINTU",
    "email": "mahfujur.mintu@polytech.edu.bd",
    "phone": "+8801948221100",
    "department": "Civil",
    "semester": 6,
    "cgpa": 3.12,
    "attendance": 74,
    "image": "https://via.placeholder.com/150",
    "status": "active"
  },
  {
    "id": 40,
    "name": "MD. AL AMIN ISLAM NAYON",
    "email": "alamin.nayon@polytech.edu.bd",
    "phone": "+8801549332211",
    "department": "Mechanical",
    "semester": 6,
    "cgpa": 3.28,
    "attendance": 80,
    "image": "https://via.placeholder.com/150",
    "status": "active"
  },
  {
    "id": 41,
    "name": "MD.TARIKUL ISLAM SHANTO",
    "email": "tarikul.shanto@polytech.edu.bd",
    "phone": "+8801650443322",
    "department": "Electrical",
    "semester": 6,
    "cgpa": 3.32,
    "attendance": 82,
    "image": "https://via.placeholder.com/150",
    "status": "active"
  },
  {
    "id": 42,
    "name": "MANIK BISWAS",
    "email": "manik.biswas@polytech.edu.bd",
    "phone": "+8801751554433",
    "department": "Civil",
    "semester": 6,
    "cgpa": 3.45,
    "attendance": 85,
    "image": "https://via.placeholder.com/150",
    "status": "active"
  },
  {
    "id": 43,
    "name": "CHONDON SARKAR",
    "email": "chondon.sarkar@polytech.edu.bd",
    "phone": "+8801852665544",
    "department": "Mechanical",
    "semester": 6,
    "cgpa": 3.78,
    "attendance": 94,
    "image": "https://via.placeholder.com/150",
    "status": "active"
  },
  {
    "id": 44,
    "name": "SAIFUL ISLAM",
    "email": "saiful.islam@polytech.edu.bd",
    "phone": "+8801953776655",
    "department": "Electrical",
    "semester": 6,
    "cgpa": 3.02,
    "attendance": 70,
    "image": "https://via.placeholder.com/150",
    "status": "active"
  },
  {
    "id": 45,
    "name": "KUSOL DAS DIP",
    "email": "kusol.dip@polytech.edu.bd",
    "phone": "+8801554887766",
    "department": "Civil",
    "semester": 6,
    "cgpa": 3.15,
    "attendance": 76,
    "image": "https://via.placeholder.com/150",
    "status": "active"
  },
  {
    "id": 46,
    "name": "MD. MASUD RANA",
    "email": "masud.rana@polytech.edu.bd",
    "phone": "+8801655998877",
    "department": "Mechanical",
    "semester": 6,
    "cgpa": 3.42,
    "attendance": 84,
    "image": "https://via.placeholder.com/150",
    "status": "active"
  },
  {
    "id": 47,
    "name": "MEHER SARKER MOLOY",
    "email": "meher.moloy@polytech.edu.bd",
    "phone": "+8801756009988",
    "department": "Electrical",
    "semester": 6,
    "cgpa": 3.6,
    "attendance": 90,
    "image": "https://via.placeholder.com/150",
    "status": "active"
  },
  {
    "id": 48,
    "name": "MD. AZIZUL ISLAM",
    "email": "azizul.islam@polytech.edu.bd",
    "phone": "+8801857110099",
    "department": "Civil",
    "semester": 6,
    "cgpa": 3.2,
    "attendance": 79,
    "image": "https://via.placeholder.com/150",
    "status": "active"
  },
  {
    "id": 49,
    "name": "MD. SHIHAB",
    "email": "md.shihab@polytech.edu.bd",
    "phone": "+8801958221100",
    "department": "Mechanical",
    "semester": 6,
    "cgpa": 3.35,
    "attendance": 82,
    "image": "https://via.placeholder.com/150",
    "status": "active"
  },
  {
    "id": 50,
    "name": "SEAM HOWLADER",
    "email": "seam.howlader@polytech.edu.bd",
    "phone": "+8801559332211",
    "department": "Electrical",
    "semester": 6,
    "cgpa": 3.52,
    "attendance": 87,
    "image": "https://via.placeholder.com/150",
    "status": "active"
  },
  {
    "id": 51,
    "name": "K. M. ASRAFUL ISLAM",
    "email": "asraful.islam@polytech.edu.bd",
    "phone": "+8801660443322",
    "department": "Civil",
    "semester": 6,
    "cgpa": 3.1,
    "attendance": 75,
    "image": "https://via.placeholder.com/150",
    "status": "active"
  },
  {
    "id": 52,
    "name": "ABU BOKOR SIDDIK HIMEL",
    "email": "abu.himel@polytech.edu.bd",
    "phone": "+8801761554433",
    "department": "Mechanical",
    "semester": 6,
    "cgpa": 3.65,
    "attendance": 91,
    "image": "https://via.placeholder.com/150",
    "status": "active"
  },
  {
    "id": 53,
    "name": "MD. NAZMUL HOSSAIN",
    "email": "nazmul.hossain@polytech.edu.bd",
    "phone": "+8801862665544",
    "department": "Electrical",
    "semester": 6,
    "cgpa": 3.28,
    "attendance": 80,
    "image": "https://via.placeholder.com/150",
    "status": "active"
  },
  {
    "id": 54,
    "name": "MD. JIHAD SHARIF",
    "email": "jihad.sharif@polytech.edu.bd",
    "phone": "+8801963776655",
    "department": "Civil",
    "semester": 6,
    "cgpa": 3.4,
    "attendance": 84,
    "image": "https://via.placeholder.com/150",
    "status": "active"
  },
  {
    "id": 55,
    "name": "MD. MAHIN HOSSAN JUBAYER",
    "email": "mahin.jubayer@polytech.edu.bd",
    "phone": "+8801564887766",
    "department": "Mechanical",
    "semester": 6,
    "cgpa": 3.58,
    "attendance": 89,
    "image": "https://via.placeholder.com/150",
    "status": "active"
  },
  {
    "id": 56,
    "name": "SHEIKH ISTIAK HOSSAIN RIDOY",
    "email": "istiak.ridoy@polytech.edu.bd",
    "phone": "+8801665998877",
    "department": "Electrical",
    "semester": 8,
    "cgpa": 3.75,
    "attendance": 93,
    "image": "https://via.placeholder.com/150",
    "status": "active"
  },
  {
    "id": 57,
    "name": "AMIT VATTACHARJEE",
    "email": "amit.v@polytech.edu.bd",
    "phone": "+8801766009988",
    "department": "Civil",
    "semester": 8,
    "cgpa": 3.1,
    "attendance": 72,
    "image": "https://via.placeholder.com/150",
    "status": "inactive"
  },
  {
    "id": 58,
    "name": "MD. ZIM",
    "email": "md.zim@polytech.edu.bd",
    "phone": "+8801867110099",
    "department": "Mechanical",
    "semester": 7,
    "cgpa": 3.25,
    "attendance": 78,
    "image": "https://via.placeholder.com/150",
    "status": "active"
  },
  {
    "id": 59,
    "name": "MD. JAHIRUL ISLAM",
    "email": "jahirul.islam@polytech.edu.bd",
    "phone": "+8801968221100",
    "department": "Electrical",
    "semester": 8,
    "cgpa": 2.85,
    "attendance": 64,
    "image": "https://via.placeholder.com/150",
    "status": "active"
  },
  {
    "id": 60,
    "name": "RASEL HOWLADAR",
    "email": "rasel.howladar@polytech.edu.bd",
    "phone": "+8801569332211",
    "department": "Civil",
    "semester": 8,
    "cgpa": 3.05,
    "attendance": 71,
    "image": "https://via.placeholder.com/150",
    "status": "inactive"
  },
  {
    "id": 61,
    "name": "MD. RAKIB-UL HASAN",
    "email": "rakibul.hasan@polytech.edu.bd",
    "phone": "+8801670443322",
    "department": "Mechanical",
    "semester": 7,
    "cgpa": 3.45,
    "attendance": 86,
    "image": "https://via.placeholder.com/150",
    "status": "active"
  },
  {
    "id": 62,
    "name": "MD. NASIR UDDIN",
    "email": "nasir.uddin@polytech.edu.bd",
    "phone": "+8801771554433",
    "department": "Electrical",
    "semester": 7,
    "cgpa": 3.18,
    "attendance": 77,
    "image": "https://via.placeholder.com/150",
    "status": "active"
  },
  {
    "id": 63,
    "name": "MD. SHAMIM MOLLA",
    "email": "shamim.molla@polytech.edu.bd",
    "phone": "+8801872665544",
    "department": "Civil",
    "semester": 7,
    "cgpa": 3.32,
    "attendance": 81,
    "image": "https://via.placeholder.com/150",
    "status": "active"
  },
  {
    "id": 64,
    "name": "MD. JIBON SARDAR",
    "email": "jibon.sardar@polytech.edu.bd",
    "phone": "+8801234567890",
    "department": "Computer",
    "semester": 7,
    "cgpa": 3.0,
    "attendance": 80,
    "image": "https://via.placeholder.com/150",
    "status": "active"
  },
  {
    "id": 65,
    "name": "MD. RAKIBUL ISLAM",
    "email": "rakibulzain@gmail.com",
    "phone": "+8801234567891",
    "department": "Computer",
    "semester": 8,
    "cgpa": 3.7,
    "attendance": 80,
    "image": "https://ibb.co.com/rKj3CD43",
    "status": "active"
  },
  {
    "id": 66,
    "name": "MD. MUSHFIQUR RAHMAN",
    "email": "mushfiqur.rahman@polytech.edu.bd",
    "phone": "+8801234567892",
    "department": "Computer",
    "semester": 8,
    "cgpa": 3.0,
    "attendance": 80,
    "image": "https://via.placeholder.com/150",
    "status": "active"
  },
  {
    "id": 67,
    "name": "MD. EMON HOWLADER",
    "email": "emon.howlader@polytech.edu.bd",
    "phone": "+8801234567893",
    "department": "Computer",
    "semester": 8,
    "cgpa": 3.3,
    "attendance": 80,
    "image": "https://via.placeholder.com/150",
    "status": "active"
  },
  {
    "id": 68,
    "name": "MANOSH TARUA",
    "email": "manosh.tarua@polytech.edu.bd",
    "phone": "+8801234567894",
    "department": "Computer",
    "semester": 8,
    "cgpa": 3.6,
    "attendance": 80,
    "image": "https://via.placeholder.com/150",
    "status": "active"
  },
  {
    "id": 69,
    "name": "SAHARIAR SULTAN MASUK",
    "email": "sahariar.masuk@polytech.edu.bd",
    "phone": "+8801234567895",
    "department": "Computer",
    "semester": 8,
    "cgpa": 3.4,
    "attendance": 80,
    "image": "https://via.placeholder.com/150",
    "status": "active"
  },
  {
    "id": 70,
    "name": "CHYON SAHA",
    "email": "chyon.saha@polytech.edu.bd",
    "phone": "+8801234567896",
    "department": "Computer",
    "semester": 8,
    "cgpa": 3.1,
    "attendance": 80,
    "image": "https://via.placeholder.com/150",
    "status": "active"
  },
  {
    "id": 71,
    "name": "SOBNOM MOSTARI",
    "email": "sobnom.mostari@polytech.edu.bd",
    "phone": "+8801234567897",
    "department": "Computer",
    "semester": 8,
    "cgpa": 3.1,
    "attendance": 80,
    "image": "https://via.placeholder.com/150",
    "status": "active"
  },
  {
    "id": 72,
    "name": "MD. RASADUL ISLAM",
    "email": "rasadul.islam@polytech.edu.bd",
    "phone": "+8801234567898",
    "department": "Computer",
    "semester": 8,
    "cgpa": 3.0,
    "attendance": 80,
    "image": "https://via.placeholder.com/150",
    "status": "active"
  },
  {
    "id": 73,
    "name": "RAKESH KARMAKAR",
    "email": "rakesh.karmakar@polytech.edu.bd",
    "phone": "+8801234567899",
    "department": "Computer",
    "semester": 8,
    "cgpa": 3.0,
    "attendance": 80,
    "image": "https://via.placeholder.com/150",
    "status": "active"
  },
  {
    "id": 74,
    "name": "ISRAT JAHAN TISA",
    "email": "israt.tisa@polytech.edu.bd",
    "phone": "+8801234567900",
    "department": "Computer",
    "semester": 8,
    "cgpa": 3.7,
    "attendance": 80,
    "image": "https://via.placeholder.com/150",
    "status": "active"
  },
  {
    "id": 75,
    "name": "MD.FUAD ALOM KHAN",
    "email": "fuad.alom@polytech.edu.bd",
    "phone": "+8801234567901",
    "department": "Computer",
    "semester": 8,
    "cgpa": 3.2,
    "attendance": 70,
    "image": "https://via.placeholder.com/150",
    "status": "active"
  },
  {
    "id": 76,
    "name": "ASHIKUR RAHAMAN",
    "email": "ashikur.rahaman@polytech.edu.bd",
    "phone": "+8801234567902",
    "department": "Computer",
    "semester": 8,
    "cgpa": 3.6,
    "attendance": 90,
    "image": "https://via.placeholder.com/150",
    "status": "active"
  },
  {
    "id": 77,
    "name": "MOSA.SABJAN",
    "email": "mosa.sabjan@polytech.edu.bd",
    "phone": "+8801234567903",
    "department": "Computer",
    "semester": 8,
    "cgpa": 3.4,
    "attendance": 80,
    "image": "https://via.placeholder.com/150",
    "status": "active"
  },
  {
    "id": 78,
    "name": "ABDULLAH RAYEAN",
    "email": "abdullah.rayean@polytech.edu.bd",
    "phone": "+8801234567904",
    "department": "Computer",
    "semester": 8,
    "cgpa": 3.1,
    "attendance": 80,
    "image": "https://via.placeholder.com/150",
    "status": "inactive"
  },
  {
    "id": 79,
    "name": "MEHEDI HASAN RATUL",
    "email": "mehedi.ratul@polytech.edu.bd",
    "phone": "+8801234567905",
    "department": "Computer",
    "semester": 6,
    "cgpa": 3.0,
    "attendance": 80,
    "image": "https://via.placeholder.com/150",
    "status": "active"
  },
  {
    "id": 80,
    "name": "CHAYON SHANKHABANIK",
    "email": "chayon.s@polytech.edu.bd",
    "phone": "+8801234567906",
    "department": "Computer",
    "semester": 8,
    "cgpa": 3.3,
    "attendance": 80,
    "image": "https://via.placeholder.com/150",
    "status": "active"
  },
  {
    "id": 81,
    "name": "ANIK DAS",
    "email": "anik.das@polytech.edu.bd",
    "phone": "+8801234567907",
    "department": "Computer",
    "semester": 8,
    "cgpa": 3.0,
    "attendance": 80,
    "image": "https://via.placeholder.com/150",
    "status": "active"
  },
  {
    "id": 82,
    "name": "MD. RAYHAN GAZI",
    "email": "rayhan.gazi@polytech.edu.bd",
    "phone": "+8801234567908",
    "department": "Computer",
    "semester": 8,
    "cgpa": 3.7,
    "attendance": 80,
    "image": "https://via.placeholder.com/150",
    "status": "active"
  },
  {
    "id": 83,
    "name": "MD.BELLAL BEPARI",
    "email": "bellal.bepari@polytech.edu.bd",
    "phone": "+8801234567909",
    "department": "Computer",
    "semester": 8,
    "cgpa": 3.2,
    "attendance": 80,
    "image": "https://via.placeholder.com/150",
    "status": "active"
  },
  {
    "id": 84,
    "name": "SAYED EHSANUL HASAN RAFI",
    "email": "ehsanul.rafi@polytech.edu.bd",
    "phone": "+8801234567910",
    "department": "Computer",
    "semester": 8,
    "cgpa": 2.0,
    "attendance": 80,
    "image": "https://via.placeholder.com/150",
    "status": "active"
  },
  {
    "id": 85,
    "name": "MD. JABER HOWLADER",
    "email": "jaber.howlader@polytech.edu.bd",
    "phone": "+8801234567911",
    "department": "Computer",
    "semester": 8,
    "cgpa": 3.6,
    "attendance": 80,
    "image": "https://via.placeholder.com/150",
    "status": "active"
  },
  {
    "id": 86,
    "name": "HASAN BAHADUR (Bongoboltur Shainik)",
    "email": "hasan.bahadur@polytech.edu.bd",
    "phone": "+8801234567912",
    "department": "Computer",
    "semester": 8,
    "cgpa": 3.3,
    "attendance": 80,
    "image": "https://via.placeholder.com/150",
    "status": "active"
  },
  {
    "id": 87,
    "name": "MD. REYAD HOSSAIN OMI",
    "email": "reyad.omi@polytech.edu.bd",
    "phone": "+8801234567913",
    "department": "Computer",
    "semester": 8,
    "cgpa": 3.4,
    "attendance": 80,
    "image": "https://via.placeholder.com/150",
    "status": "active"
  },
  {
    "id": 88,
    "name": "ISRAFIL MRIDHA",
    "email": "israfil.mridha@polytech.edu.bd",
    "phone": "+8801234567914",
    "department": "Computer",
    "semester": 8,
    "cgpa": 3.6,
    "attendance": 80,
    "image": "https://via.placeholder.com/150",
    "status": "active"
  },
  {
    "id": 89,
    "name": "TAMIMA KHANOM",
    "email": "tamima.khanom@polytech.edu.bd",
    "phone": "+8801234567915",
    "department": "Computer",
    "semester": 6,
    "cgpa": 3.2,
    "attendance": 80,
    "image": "https://via.placeholder.com/150",
    "status": "active"
  },
  {
    "id": 90,
    "name": "RABIUL ISLAM",
    "email": "rabiul.islam@polytech.edu.bd",
    "phone": "+8801234567916",
    "department": "Computer",
    "semester": 6,
    "cgpa": 3.3,
    "attendance": 80,
    "image": "https://via.placeholder.com/150",
    "status": "active"
  },
  {
    "id": 91,
    "name": "TAOHIDUL ISLAM",
    "email": "taohidul.islam@polytech.edu.bd",
    "phone": "+8801234567917",
    "department": "Computer",
    "semester": 8,
    "cgpa": 3.6,
    "attendance": 80,
    "image": "https://via.placeholder.com/150",
    "status": "active"
  },
  {
    "id": 92,
    "name": "MD. HEDAYET HOSSAIN SUVO",
    "email": "hedayet.suvo@polytech.edu.bd",
    "phone": "+8801234567918",
    "department": "Computer",
    "semester": 8,
    "cgpa": 3.2,
    "attendance": 80,
    "image": "https://via.placeholder.com/150",
    "status": "active"
  },
  {
    "id": 93,
    "name": "MD JIHAD",
    "email": "md.jihad@polytech.edu.bd",
    "phone": "+8801234567919",
    "department": "Computer",
    "semester": 8,
    "cgpa": 3.6,
    "attendance": 80,
    "image": "https://via.placeholder.com/150",
    "status": "active"
  },
  {
    "id": 94,
    "name": "SHISHIR MANDAL",
    "email": "shishir.mandal@polytech.edu.bd",
    "phone": "+8801234567920",
    "department": "Computer",
    "semester": 8,
    "cgpa": 3.3,
    "attendance": 80,
    "image": "https://via.placeholder.com/150",
    "status": "active"
  },
  {
    "id": 95,
    "name": "ASRAFUL ISLAM",
    "email": "asraful.islam@polytech.edu.bd",
    "phone": "+8801234567921",
    "department": "Computer",
    "semester": 8,
    "cgpa": 3.5,
    "attendance": 80,
    "image": "https://via.placeholder.com/150",
    "status": "active"
  },
  {
    "id": 96,
    "name": "ABDULLAH ALL SIAM",
    "email": "abdullah.siam@polytech.edu.bd",
    "phone": "+8801234567922",
    "department": "Computer",
    "semester": 8,
    "cgpa": 3.4,
    "attendance": 80,
    "image": "https://via.placeholder.com/150",
    "status": "active"
  },
  {
    "id": 97,
    "name": "RISUL AMIN REMON",
    "email": "risul.remon@polytech.edu.bd",
    "phone": "+8801234567923",
    "department": "Computer",
    "semester": 8,
    "cgpa": 3.7,
    "attendance": 80,
    "image": "https://via.placeholder.com/150",
    "status": "active"
  },
  {
    "id": 98,
    "name": "TAUFIQ HOSSAIN ARNOB",
    "email": "taufiq.arnob@polytech.edu.bd",
    "phone": "+8801234567924",
    "department": "Computer",
    "semester": 8,
    "cgpa": 3.1,
    "attendance": 80,
    "image": "https://via.placeholder.com/150",
    "status": "active"
  },
  {
    "id": 99,
    "name": "HM NURUL AHSAN SAYEM",
    "email": "nurul.sayem@polytech.edu.bd",
    "phone": "+8801234567925",
    "department": "Computer",
    "semester": 8,
    "cgpa": 3.7,
    "attendance": 80,
    "image": "https://via.placeholder.com/150",
    "status": "active"
  },
  {
    "id": 100,
    "name": "ANIK CHANDRA ROY",
    "email": "anik.roy@polytech.edu.bd",
    "phone": "+8801234567926",
    "department": "Computer",
    "semester": 6,
    "cgpa": 3.0,
    "attendance": 80,
    "image": "https://via.placeholder.com/150",
    "status": "active"
  },
  {
    "id": 101,
    "name": "MD.TANVIR ISLAM CHAON",
    "email": "tanvir.chaon@polytech.edu.bd",
    "phone": "+8801234567927",
    "department": "Computer",
    "semester": 8,
    "cgpa": 3.5,
    "attendance": 80,
    "image": "https://via.placeholder.com/150",
    "status": "active"
  },
  {
    "id": 102,
    "name": "DIPTO SANDAR",
    "email": "dipto.sandar@polytech.edu.bd",
    "phone": "+8801234567928",
    "department": "Computer",
    "semester": 8,
    "cgpa": 3.4,
    "attendance": 80,
    "image": "https://via.placeholder.com/150",
    "status": "active"
  },
  {
    "id": 103,
    "name": "MD. NIROB HOSSEN",
    "email": "nirob.hossen@polytech.edu.bd",
    "phone": "+8801234567929",
    "department": "Computer",
    "semester": 8,
    "cgpa": 3.1,
    "attendance": 80,
    "image": "https://via.placeholder.com/150",
    "status": "active"
  },
  {
    "id": 104,
    "name": "MD. MUTASIM AMIN RIDMI",
    "email": "mutasim.ridmi@polytech.edu.bd",
    "phone": "+8801234567930",
    "department": "Computer",
    "semester": 8,
    "cgpa": 3.7,
    "attendance": 80,
    "image": "https://via.placeholder.com/150",
    "status": "active"
  },
  {
    "id": 105,
    "name": "MD. TORIKUL ISLAM SUVA",
    "email": "torikul.suva@polytech.edu.bd",
    "phone": "+8801234567931",
    "department": "Computer",
    "semester": 8,
    "cgpa": 1.9,
    "attendance": 80,
    "image": "https://via.placeholder.com/150",
    "status": "active"
  },
  {
    "id": 106,
    "name": "MD. SABBIR HOSAN",
    "email": "sabbir.hosan@polytech.edu.bd",
    "phone": "+8801234567932",
    "department": "Computer",
    "semester": 8,
    "cgpa": 3.6,
    "attendance": 80,
    "image": "https://via.placeholder.com/150",
    "status": "active"
  },
  {
    "id": 107,
    "name": "MEHEDI HASAN",
    "email": "mehedi.hasan@polytech.edu.bd",
    "phone": "+8801234567933",
    "department": "Computer",
    "semester": 8,
    "cgpa": 3.8,
    "attendance": 80,
    "image": "https://via.placeholder.com/150",
    "status": "active"
  },
  {
    "id":  108,
    "name": "MAHIMA TASNIM",
    "email": "mahima.tasnim@polytech.edu.bd",
    "phone": "+8801234567934",
    "department": "Computer",
    "semester": 8,
    "cgpa": 3.3,
    "attendance": 80,
    "image": "https://via.placeholder.com/150",
    "status": "active"
  },
  {
    "id": 109,
    "name": "MST SABINA AKTAR",
    "email": "sabina.aktar@polytech.edu.bd",
    "phone": "+8801234567935",
    "department": "Computer",
    "semester": 8,
    "cgpa": 3.6,
    "attendance": 80,
    "image": "https://via.placeholder.com/150",
    "status": "active"
  },
  {
    "id": 110,
    "name": "MD. TAIFUR RAHAMAN GAZI",
    "email": "taifur.gazi@polytech.edu.bd",
    "phone": "+8801234567936",
    "department": "Computer",
    "semester": 8,
    "cgpa": 3.3,
    "attendance": 80,
    "image": "https://via.placeholder.com/150",
    "status": "active"
  },
  {
    "id": 111,
    "name": "SUMAIA AKTER SANTONA",
    "email": "sumaia.santona@polytech.edu.bd",
    "phone": "+8801234567937",
    "department": "Computer",
    "semester": 8,
    "cgpa": 3.3,
    "attendance": 80,
    "image": "https://via.placeholder.com/150",
    "status": "active"
  },
  {
    "id": 112,
    "name": "MD. RAISUL ISLAM ABIR",
    "email": "raisul.abir@polytech.edu.bd",
    "phone": "+8801234567938",
    "department": "Computer",
    "semester": 8,
    "cgpa": 3.2,
    "attendance": 80,
    "image": "https://via.placeholder.com/150",
    "status": "active"
  },
  {
    "id": 113,
    "name": "MD. REDWAN AHAMED",
    "email": "redwan.ahamed@polytech.edu.bd",
    "phone": "+8801234567939",
    "department": "Computer",
    "semester": 8,
    "cgpa": 3.7,
    "attendance": 80,
    "image": "https://via.placeholder.com/150",
    "status": "active"
  },
  {
    "id": 114,
    "name": "ABDULLAH AL ABID",
    "email": "abdullah.abid@polytech.edu.bd",
    "phone": "+8801234567940",
    "department": "Computer",
    "semester": 8,
    "cgpa": 3.4,
    "attendance": 80,
    "image": "https://via.placeholder.com/150",
    "status": "active"
  },
  {
    "id": 115,
    "name": "MOYEN ALAM SANTO",
    "email": "moyen.santo@polytech.edu.bd",
    "phone": "+8801234567941",
    "department": "Computer",
    "semester": 8,
    "cgpa": 3.5,
    "attendance": 80,
    "image": "https://via.placeholder.com/150",
    "status": "active"
  },
  {
    "id": 116,
    "name": "YEASIN KHAN",
    "email": "yeasin.khan@polytech.edu.bd",
    "phone": "+8801234567942",
    "department": "Computer",
    "semester": 8,
    "cgpa": 3.3,
    "attendance": 80,
    "image": "https://via.placeholder.com/150",
    "status": "active"
  },
  {
    "id": 117,
    "name": "MD. MUSHFIQUR RAHMAN",
    "email": "mushfiqur.rahman.v2@polytech.edu.bd",
    "phone": "+8801234567943",
    "department": "Computer",
    "semester": 8,
    "cgpa": 3.6,
    "attendance": 80,
    "image": "https://via.placeholder.com/150",
    "status": "active"
  },
  {
    "id": 118,
    "name": "MD. ABDULLA AL RAJIN",
    "email": "abdullah.rajin@polytech.edu.bd",
    "phone": "+8801234567944",
    "department": "Computer",
    "semester": 8,
    "cgpa": 3.3,
    "attendance": 80,
    "image": "https://via.placeholder.com/150",
    "status": "active"
  },
  {
    "id": 119,
    "name": "RIDOY SIKDER",
    "email": "ridoy.sikder@polytech.edu.bd",
    "phone": "+8801234567945",
    "department": "Computer",
    "semester": 8,
    "cgpa": 3.3,
    "attendance": 80,
    "image": "https://via.placeholder.com/150",
    "status": "active"
  },
  {
    "id": 120,
    "name": "MD. SHUVO KHAN",
    "email": "shuvo.khan@polytech.edu.bd",
    "phone": "+8801234567946",
    "department": "Computer",
    "semester": 8,
    "cgpa": 3.6,
    "attendance": 80,
    "image": "https://via.placeholder.com/150",
    "status": "active"
  },
  {
    "id": 121,
    "name": "SHISHIR PAL ANIK",
    "email": "shishir.anik@polytech.edu.bd",
    "phone": "+8801234567947",
    "department": "Computer",
    "semester": 8,
    "cgpa": 3.2,
    "attendance": 80,
    "image": "https://via.placeholder.com/150",
    "status": "active"
  }

]